mycobot_mcp/__init__.py
mycobot_mcp/__main__.py
mycobot_mcp/server.py
robotarm_mcp_p340-0.1.0.dist-info/licenses/LICENSE
robotarm_mcp_p340-0.1.0.dist-info/METADATA
robotarm_mcp_p340-0.1.0.dist-info/WHEEL
robotarm_mcp_p340-0.1.0.dist-info/entry_points.txt
robotarm_mcp_p340-0.1.0.dist-info/top_level.txt
robotarm_mcp_p340-0.1.0.dist-info/RECORD
