Metadata-Version: 2.4
Name: robotarm-mcp-p340
Version: 0.1.0
Summary: MCP Server for controlling ElephantRobotics MyCobot robotic arms via natural language
Author-email: FanGe <archifancy@gmail.com>, guoyuaarg <aargwangguoyu@outlook.com>
License: MIT
Project-URL: Homepage, https://github.com/AI-FanGe/RobotArm-MCP-P340
Project-URL: Documentation, https://github.com/AI-FanGe/RobotArm-MCP-P340#readme
Project-URL: Repository, https://github.com/AI-FanGe/RobotArm-MCP-P340.git
Project-URL: Issues, https://github.com/AI-FanGe/RobotArm-MCP-P340/issues
Keywords: mcp,mycobot,robotics,elephantrobotics,robot-arm
Classifier: Development Status :: 3 - Alpha
Classifier: Intended Audience :: Developers
Classifier: License :: OSI Approved :: MIT License
Classifier: Programming Language :: Python :: 3
Classifier: Programming Language :: Python :: 3.10
Classifier: Topic :: Software Development :: Libraries :: Python Modules
Requires-Python: >=3.10
License-File: LICENSE
Requires-Dist: mcp>=1.10.0
Requires-Dist: pymycobot>=3.9.0
Requires-Dist: pyserial>=3.5
Dynamic: license-file
